pypal_api/__init__.py
pypal_api/exceptions.py
pypal_api/pypal_dates.py
pypal_api/pypal_pandas.py
pypal_api-0.1.6.dist-info/LICENSE
pypal_api-0.1.6.dist-info/METADATA
pypal_api-0.1.6.dist-info/WHEEL
pypal_api-0.1.6.dist-info/top_level.txt
pypal_api-0.1.6.dist-info/RECORD
