Metadata-Version: 2.1
Name: pypal-api
Version: 0.1.6
Summary: A collection of helper functions to ease API development
Home-page: https://github.com/IvanCampos11/PyPal-API
Author: Ivan Campos
License: UNKNOWN
Platform: UNKNOWN
Classifier: Programming Language :: Python :: 3.8
Classifier: License :: OSI Approved :: MIT License
Classifier: Operating System :: OS Independent
Requires-Python: >=3.8
License-File: LICENSE
Requires-Dist: numpy (>=1.21.4)
Requires-Dist: pandas (>=1.3.4)
Requires-Dist: ShopifyAPI (>=9.0.0)
Requires-Dist: requests
Requires-Dist: fastapi (>=0.70.0)
Requires-Dist: gspread (>=5.0.0)
Requires-Dist: oauth2client (>=4.1.3)
Requires-Dist: monday (>=1.2.7)
Requires-Dist: python-dotenv (>=0.19.2)
